pynada/__init__.py
pynada/commons.py
pynada/create_and_import.py
pynada/manage_and_update.py
pynada/search_and_browse.py
pynada/utils.py
pynada-0.0.35.dist-info/METADATA
pynada-0.0.35.dist-info/WHEEL
pynada-0.0.35.dist-info/top_level.txt
pynada-0.0.35.dist-info/RECORD
