Metadata-Version: 2.1
Name: pynada
Version: 0.0.35
Summary: Python client for NADA API
Home-page: https://github.com/kl9ch/PyNADA
Author: Kamwoo Lee
License: UNKNOWN
Platform: UNKNOWN
Requires-Dist: requests
Requires-Dist: pandas
Requires-Dist: pathlib
Requires-Dist: validators
Requires-Dist: pdf2image
